sciebo_rds_cli/__init__.py
sciebo_rds_cli/main.py
sciebo_rds_cli-0.1.6.dist-info/entry_points.txt
sciebo_rds_cli-0.1.6.dist-info/WHEEL
sciebo_rds_cli-0.1.6.dist-info/METADATA
sciebo_rds_cli-0.1.6.dist-info/RECORD
