Metadata-Version: 2.1
Name: sciebo-rds-cli
Version: 0.1.6
Summary: Script for install sciebo RDS in sciebo
Home-page: https://github.com/Sciebo-RDS/Sciebo-RDS-CLI
License: MIT
Author: Peter Heiss
Author-email: peter.heiss@uni-muenster.de
Requires-Python: >=3.8,<4.0
Classifier: License :: OSI Approved :: MIT License
Classifier: Programming Language :: Python :: 3
Classifier: Programming Language :: Python :: 3.8
Classifier: Programming Language :: Python :: 3.9
Classifier: Programming Language :: Python :: 3.10
Requires-Dist: PyYAML (>=6.0,<7.0)
Requires-Dist: click (>=8.0.4,<9.0.0)
Requires-Dist: kubernetes (>=21.7.0,<22.0.0)
Requires-Dist: paramiko (>=2.9.2,<3.0.0)
Project-URL: Repository, https://github.com/Sciebo-RDS/Sciebo-RDS-CLI
